pymystrom/__init__.py
pymystrom/bulb.py
pymystrom/cli.py
pymystrom/device_types.py
pymystrom/discovery.py
pymystrom/exceptions.py
pymystrom/pir.py
pymystrom/switch.py
python_mystrom-2.6.0.dist-info/METADATA
python_mystrom-2.6.0.dist-info/WHEEL
python_mystrom-2.6.0.dist-info/entry_points.txt
python_mystrom-2.6.0.dist-info/licenses/LICENSE
python_mystrom-2.6.0.dist-info/RECORD
