Metadata-Version: 2.4
Name: python-mystrom
Version: 2.6.0
Summary: Asynchronous Python API client for interacting with myStrom devices
License: MIT
License-File: LICENSE
Keywords: myStrom,API,client,asynchronous
Author: Fabian Affolter
Author-email: fabian@affolter-engineering.ch
Requires-Python: >=3.11
Classifier: License :: OSI Approved :: MIT License
Classifier: Programming Language :: Python :: 3
Classifier: Programming Language :: Python :: 3.11
Classifier: Programming Language :: Python :: 3.12
Classifier: Programming Language :: Python :: 3.13
Classifier: Programming Language :: Python :: 3.14
Requires-Dist: aiohttp
Requires-Dist: click
Requires-Dist: requests
Project-URL: Homepage, https://github.com/home-assistant-ecosystem/python-mystrom
Project-URL: Repository, https://github.com/home-assistant-ecosystem/python-mystrom
